hexagon/__init__.py
hexagon/django_integration.py
hexagon/flask_integration.py
hexagon/hexagon.py
hexagon_sdk-1.0.0.dist-info/METADATA
hexagon_sdk-1.0.0.dist-info/WHEEL
hexagon_sdk-1.0.0.dist-info/top_level.txt
hexagon_sdk-1.0.0.dist-info/RECORD
