Metadata-Version: 2.4
Name: hexagon-sdk
Version: 1.0.0
Summary: Make your website AI-readable by ChatGPT, Perplexity, Claude and other AI platforms
Home-page: https://github.com/hexagon-labs/hexagon-python-sdk
Author: Hexagon Labs
Author-email: hello@joinhexagon.com
Keywords: ai gpt chatgpt claude perplexity seo ai-search crawler bot
Classifier: Development Status :: 4 - Beta
Classifier: Intended Audience :: Developers
Classifier: Topic :: Software Development :: Libraries :: Python Modules
Classifier: License :: OSI Approved :: MIT License
Classifier: Programming Language :: Python :: 3
Classifier: Programming Language :: Python :: 3.7
Classifier: Programming Language :: Python :: 3.8
Classifier: Programming Language :: Python :: 3.9
Classifier: Programming Language :: Python :: 3.10
Classifier: Programming Language :: Python :: 3.11
Classifier: Framework :: Flask
Classifier: Framework :: Django
Requires-Python: >=3.7
Requires-Dist: requests>=2.25.0
Provides-Extra: flask
Requires-Dist: flask>=2.0.0; extra == "flask"
Provides-Extra: django
Requires-Dist: django>=3.2.0; extra == "django"
Dynamic: author
Dynamic: author-email
Dynamic: classifier
Dynamic: description
Dynamic: description-content-type
Dynamic: home-page
Dynamic: keywords
Dynamic: provides-extra
Dynamic: requires-dist
Dynamic: requires-python
Dynamic: summary
